[
  {
    "key": "ctrl+g",
    "command": "editor.action.addSelectionToNextFindMatch"
  },
  {
    "key": "cmd+1",
    "command": "workbench.action.focusSideBar"
  },
  {
    "key": "cmd+1",
    "command": "workbench.action.toggleSidebarVisibility",
    "when": "sideBarFocus"
  },
  {
    "key": "enter",
    "command": "list.select",
    "when": "sideBarFocus"
  },
  {
    "key": "cmd+shift+a",
    "command": "workbench.action.showCommands"
  },
  {
    "key": "cmd+shift+1",
    "command": "workbench.action.toggleActivityBarVisibility"
  },
  {
    "key": "cmd+e",
    "command": "workbench.action.quickOpen"
  },
  {
    "key": "cmd+d",
    "command": "editor.action.copyLinesDownAction",
    "when": "editorTextFocus && !editorReadonly"
  },
  {
    "key": "ctrl+alt+cmd+m",
    "command": "notifications.clearAll"
  },
  {
    "key": "ctrl+alt+cmd+t",
    "command": "workbench.action.terminal.toggleTerminal"
  },
  {
    "key": "cmd+2",
    "command": "workbench.action.terminal.toggleTerminal"
  },
  {
    "key": "cmd+shift+s",
    "command": "workbench.files.action.showActiveFileInExplorer",
    "when": "editorTextFocus"
  },
  {
    "key": "escape",
    "command": "workbench.action.focusActiveEditorGroup",
    "when": "!editorTextFocus"
  }
]